ansible_discover-0.2.1.dist-info/METADATA
ansible_discover-0.2.1.dist-info/RECORD
ansible_discover-0.2.1.dist-info/WHEEL
ansible_discover-0.2.1.dist-info/entry_points.txt
ansible_discover-0.2.1.dist-info/top_level.txt
ansiblediscover/__init__.py
ansiblediscover/cli.py
ansiblediscover/entity/__init__.py
ansiblediscover/entity/entities.py
ansiblediscover/entity/play.py
ansiblediscover/entity/playbook.py
ansiblediscover/entity/task.py
ansiblediscover/entity/tasklist.py
ansiblediscover/entity/role/__init__.py
ansiblediscover/graph/__init__.py
ansiblediscover/graph/dependencies.py
ansiblediscover/graph/node.py
ansiblediscover/graph/traversal.py
ansiblediscover/utils/__init__.py
ansiblediscover/utils/fs.py
