Metadata-Version: 2.1
Name: ansible-discover
Version: 0.2.1
Summary: Discover both dependants and dependencies of Ansible playbooks and roles, respectively
Home-page: https://github.com/croesnick/ansible-discover
Author: Carsten Rösnick-Neugebauer
Author-email: croesnick@gmail.com
License: MIT
Download-URL: https://github.com/croesnick/ansible-discover/archive/v0.2.1.tar.gz
Keywords: ansible,testing,ci
Platform: UNKNOWN
Classifier: Development Status :: 3 - Alpha
Classifier: Environment :: Console
Classifier: Intended Audience :: Developers
Classifier: License :: OSI Approved :: MIT License
Classifier: Programming Language :: Python :: 3
Classifier: Programming Language :: Python :: 3.6
Classifier: Programming Language :: Python :: 3.7
Classifier: Topic :: Software Development :: Build Tools
Classifier: Topic :: Software Development :: Testing
Classifier: Topic :: Utilities
Requires-Python: >=3.6
Requires-Dist: PyYAML (~=3.12)
Requires-Dist: click (~=6.7)
Requires-Dist: ruamel.yaml (<=0.15.37)
